README.rst
setup.cfg
setup.py
ezcolorizer/__init__.py
ezcolorizer.egg-info/PKG-INFO
ezcolorizer.egg-info/SOURCES.txt
ezcolorizer.egg-info/dependency_links.txt
ezcolorizer.egg-info/entry_points.txt
ezcolorizer.egg-info/top_level.txt