Metadata-Version: 1.1
Name: ezcolorizer
Version: 1.0.4
Summary: Add color to strings in python, great for menus and printing output
Home-page: https://github.com/the-portly-penguin/ezcolorizer
Author: The Portly Penguin
Author-email: admin@theportlypenguin.net
License: MIT
Keywords: color setuptools development administration script
Platform: UNKNOWN
Classifier: Environment :: Console
Classifier: Operating System :: POSIX
Classifier: Intended Audience :: Developers
Classifier: Intended Audience :: System Administrators
Classifier: Programming Language :: Python
